dist_truncate/__init__.py
dist_truncate/truncate.py
dist_truncate-0.2.0.dist-info/LICENSE
dist_truncate-0.2.0.dist-info/METADATA
dist_truncate-0.2.0.dist-info/WHEEL
dist_truncate-0.2.0.dist-info/top_level.txt
dist_truncate-0.2.0.dist-info/RECORD
