Metadata-Version: 2.1
Name: dist-truncate
Version: 0.2.0
Summary: Easily truncate scipy distributions.
Home-page: https://github.com/schoennenbeck/dist-truncate
Author: Sebastian Schönnenbeck
Author-email: schoennenbeck@gmail.com
License: MIT
Requires-Python: >=3.6
License-File: LICENSE
Requires-Dist: scipy (>=1)
Provides-Extra: dev
Requires-Dist: black ; extra == 'dev'
Requires-Dist: isort ; extra == 'dev'
Requires-Dist: mypy ; extra == 'dev'
Requires-Dist: pre-commit ; extra == 'dev'
Requires-Dist: pytest ; extra == 'dev'
Requires-Dist: pytest-cov ; extra == 'dev'
Requires-Dist: coveralls ; extra == 'dev'
Requires-Dist: coverage ; extra == 'dev'
Requires-Dist: flake8 ; extra == 'dev'
